{"nodes": [{"id": "support_compatibility_dietaryhierarchy", "label": "DietaryHierarchy Dataclass", "file_type": "code", "source_file": "scripts/support/compatibility.py", "source_location": "44-58", "source_url": null, "captured_at": null, "author": null, "contributor": null}, {"id": "support_compatibility_buildhierarchy", "label": "build_hierarchy Function", "file_type": "code", "source_file": "scripts/support/compatibility.py", "source_location": "61-105", "source_url": null, "captured_at": null, "author": null, "contributor": null}, {"id": "support_compatibility_isitemcompatible", "label": "is_item_compatible Function", "file_type": "code", "source_file": "scripts/support/compatibility.py", "source_location": "124-149", "source_url": null, "captured_at": null, "author": null, "contributor": null}, {"id": "support_compatibility_itemincompatibilityids", "label": "item_incompatibility_ids Function", "file_type": "code", "source_file": "scripts/support/compatibility.py", "source_location": "152-197", "source_url": null, "captured_at": null, "author": null, "contributor": null}, {"id": "support_compatibility_hasoptedout", "label": "has_opted_out Function", "file_type": "code", "source_file": "scripts/support/compatibility.py", "source_location": "116-121", "source_url": null, "captured_at": null, "author": null, "contributor": null}, {"id": "support_compatibility_negativekeywords", "label": "NEGATIVE_KEYWORDS Constant", "file_type": "code", "source_file": "scripts/support/compatibility.py", "source_location": "37-38", "source_url": null, "captured_at": null, "author": null, "contributor": null}], "edges": [{"source": "support_compatibility_buildhierarchy", "target": "support_compatibility_dietaryhierarchy", "relation": "calls", "confidence": "EXTRACTED", "confidence_score": 1.0, "source_file": "scripts/support/compatibility.py", "source_location": "100", "weight": 1.0}, {"source": "support_compatibility_isitemcompatible", "target": "support_compatibility_itemincompatibilityids", "relation": "calls", "confidence": "EXTRACTED", "confidence_score": 1.0, "source_file": "scripts/support/compatibility.py", "source_location": "147", "weight": 1.0}, {"source": "support_compatibility_hasoptedout", "target": "support_compatibility_dietaryhierarchy", "relation": "references", "confidence": "EXTRACTED", "confidence_score": 1.0, "source_file": "scripts/support/compatibility.py", "source_location": "121", "weight": 1.0}, {"source": "support_compatibility_itemincompatibilityids", "target": "support_compatibility_negativekeywords", "relation": "references", "confidence": "EXTRACTED", "confidence_score": 1.0, "source_file": "scripts/support/compatibility.py", "source_location": "193", "weight": 1.0}, {"source": "support_compatibility_negativekeywords", "target": "data_dietary_keywords_negativekeywords", "relation": "references", "confidence": "EXTRACTED", "confidence_score": 1.0, "source_file": "scripts/support/compatibility.py", "source_location": "37-38", "weight": 1.0}, {"source": "support_compatibility_itemincompatibilityids", "target": "support_records_menuitemfields", "relation": "references", "confidence": "EXTRACTED", "confidence_score": 1.0, "source_file": "scripts/support/compatibility.py", "source_location": "152", "weight": 1.0}, {"source": "support_compatibility_buildhierarchy", "target": "support_records_dietaryrestrictionfields", "relation": "references", "confidence": "EXTRACTED", "confidence_score": 1.0, "source_file": "scripts/support/compatibility.py", "source_location": "61", "weight": 1.0}], "hyperedges": [{"id": "dietary_compatibility_pipeline", "label": "Dietary Compatibility Check Pipeline", "nodes": ["support_compatibility_buildhierarchy", "support_compatibility_isitemcompatible", "data_dietary_keywords_negativekeywords"], "relation": "implement", "confidence": "EXTRACTED", "confidence_score": 0.95, "source_file": "scripts/support/compatibility.py"}]}